beige/__init__.py
beige-0.1.2.dist-info/LICENSE
beige-0.1.2.dist-info/METADATA
beige-0.1.2.dist-info/WHEEL
beige-0.1.2.dist-info/top_level.txt
beige-0.1.2.dist-info/RECORD
