Metadata-Version: 2.1
Name: beige
Version: 0.1.2
Summary: Python exchange engine
Home-page: https://github.com/alienbrett/beige
Author: Brett Graves
Author-email: alienbrett648@gmail.com
License: MIT
Platform: UNKNOWN
Classifier: License :: OSI Approved :: MIT License
Classifier: Programming Language :: Python
Classifier: Programming Language :: Python :: 3
Classifier: Programming Language :: Python :: 3.6
Classifier: Programming Language :: Python :: Implementation :: CPython
Classifier: Programming Language :: Python :: Implementation :: PyPy
Requires-Python: >=3.6.0
Requires-Dist: pandas
Requires-Dist: sortedcontainers
